gdax/__init__.py
gdax/orderbook.py
gdax/trader.py
gdax/utils.py
gdax_python_api-0.1.dist-info/DESCRIPTION.rst
gdax_python_api-0.1.dist-info/METADATA
gdax_python_api-0.1.dist-info/RECORD
gdax_python_api-0.1.dist-info/WHEEL
gdax_python_api-0.1.dist-info/metadata.json
gdax_python_api-0.1.dist-info/top_level.txt
